{"id":"archive-monster-item-5030-zombie-captain-s-spiritual-body","section":"monsters","group":"s-z","title":"Zombie Captain's Spiritual Body (монстр)","summary":"Черновая карточка монстра. Базовая страница создана автоматически, чтобы ссылка из дропа не вела в пустоту.","eyebrow":"Монстры","meta":[{"label":"Статус","value":"Черновик автогенерации"},{"label":"ID","value":"5030"}],"intro":[],"checklist":[],"steps":[],"rewards":[],"tips":[],"related":[],"order":9999,"layout":"detail","sidebarFacts":[{"label":"Источник","value":"Автофикc ссылок дропа/спойла"},{"label":"Заполнение","value":"Добавь данные в админ-панели"}],"source":{},"aliases":[],"heroImage":"https://l2int.ru/images/armor_weapon/armor/NG/Leather_Cap.jpg","blocks":[{"id":"archive-monster-item-5030-zombie-captain-s-spiritual-body-draft","type":"prose","title":"Карточка в работе","paragraphs":["Страница создана автоматически, чтобы ссылка из таблиц дропа и спойла открывалась корректно.","Добавь характеристики, локации, дроп и дополнительную информацию через админ-панель."]},{"id":"archive-monster-item-5030-zombie-captain-s-spiritual-body-refs","type":"table","title":"Где встречается ссылка","columns":[{"key":"source","label":"Материал","align":"","width":""},{"key":"note","label":"Примечание","align":"","width":""}],"rows":[{"id":"archive-monster-item-5030-zombie-captain-s-spiritual-body-ref-1","title":"","href":"","cells":[{"value":"Composite Helmet (Композитный Шлем)","href":"/pages/article.html?article=armor-item-934-composite-helmet","html":""},{"value":"Переход был восстановлен автоматически","href":"","html":""}],"meta":[]},{"id":"archive-monster-item-5030-zombie-captain-s-spiritual-body-ref-2","title":"","href":"","cells":[{"value":"Shining Circlet (Сверкающая Диадема)","href":"/pages/article.html?article=armor-item-935-shining-circlet","html":""},{"value":"Переход был восстановлен автоматически","href":"","html":""}],"meta":[]},{"id":"archive-monster-item-5030-zombie-captain-s-spiritual-body-ref-3","title":"","href":"","cells":[{"value":"Tower Shield (Башенный Щит)","href":"/pages/article.html?article=armor-item-416-tower-shield","html":""},{"value":"Переход был восстановлен автоматически","href":"","html":""}],"meta":[]},{"id":"archive-monster-item-5030-zombie-captain-s-spiritual-body-ref-4","title":"","href":"","cells":[{"value":"Composite Shield (Композитный Щит)","href":"/pages/article.html?article=armor-item-417-composite-shield","html":""},{"value":"Переход был восстановлен автоматически","href":"","html":""}],"meta":[]},{"id":"archive-monster-item-5030-zombie-captain-s-spiritual-body-ref-5","title":"","href":"","cells":[{"value":"Thread (Нитки)","href":"/pages/article.html?article=resource-item-105-thread","html":""},{"value":"Переход был восстановлен автоматически","href":"","html":""}],"meta":[]},{"id":"archive-monster-item-5030-zombie-captain-s-spiritual-body-ref-6","title":"","href":"","cells":[{"value":"Mithril Ore (Мифриловая Руда)","href":"/pages/article.html?article=resource-item-109-mithril-ore","html":""},{"value":"Переход был восстановлен автоматически","href":"","html":""}],"meta":[]},{"id":"archive-monster-item-5030-zombie-captain-s-spiritual-body-ref-7","title":"","href":"","cells":[{"value":"Silver Nugget (Серебряный Слиток)","href":"/pages/article.html?article=resource-item-107-silver-nugget","html":""},{"value":"Переход был восстановлен автоматически","href":"","html":""}],"meta":[]},{"id":"archive-monster-item-5030-zombie-captain-s-spiritual-body-ref-8","title":"","href":"","cells":[{"value":"Enria (Энрия)","href":"/pages/article.html?article=resource-item-114-enria","html":""},{"value":"Переход был восстановлен автоматически","href":"","html":""}],"meta":[]},{"id":"archive-monster-item-5030-zombie-captain-s-spiritual-body-ref-9","title":"","href":"","cells":[{"value":"Metallic Fiber (Металлическое Волокно)","href":"/pages/article.html?article=resource-item-137-metallic-fiber","html":""},{"value":"Переход был восстановлен автоматически","href":"","html":""}],"meta":[]}],"compact":false}]}