{"id":"archive-npc-item-5486-roxxy","section":"npc","group":"catalog","title":"Roxxy (Рокси)","summary":"Gatekeeper Roxxy (Рокси) - местонахождение, квесты, характеристики","eyebrow":"NPC","meta":[],"intro":["Можно взять квест:"],"checklist":[],"steps":[],"rewards":[],"tips":[],"related":[],"order":144,"layout":"detail","sidebarFacts":[],"source":{"url":"https://web.archive.org/web/20220628004057/https://l2int.ru/npc/item/5486-roxxy","archivedAt":"20220628004057","path":"npc/item/5486-roxxy","snapshot":"data/raw/archive/npc-item-5486-roxxy--20220628004057.html","sourceType":"local-archive"},"aliases":["roxxy (рокси)","roxxy","рокси"],"heroImage":"/assets/img/archive/quest-letter-white-bd40318cd2c3.jpg","blocks":[{"id":"npc-item-5486-roxxy-block-1","type":"list","title":"","style":"unordered","items":["Interlude"]},{"id":"npc-item-5486-roxxy-block-2","type":"table","title":"Interlude","columns":[{"key":"column-1","label":"Колонка 1","align":"","width":""},{"key":"column-2","label":"Колонка 2","align":"","width":""},{"key":"column-3","label":"Колонка 3","align":"","width":""}],"rows":[{"id":"row-1","title":"","href":"/pages/article.html?article=archive-npc-item-5486-roxxy","cells":[{"value":"Gatekeeper / Уровень / 70 / Раса / Humans / Агрессивный / Нет / Количество HP / 3862 / Количество MP / 1493 / Количество EXP / - / Количество SP / -","href":"/pages/article.html?article=archive-npc-item-5486-roxxy","html":""},{"value":"","href":"/pages/article.html?article=archive-npc-item-5486-roxxy","html":""},{"value":"Скриншот не загружен","href":"/pages/article.html?article=archive-npc-item-5486-roxxy","html":""}],"meta":[]},{"id":"row-2","title":"","href":"/pages/article.html?article=archive-npc-item-5486-roxxy","cells":[{"value":"Gatekeeper","href":"/pages/article.html?article=archive-npc-item-5486-roxxy","html":""},{"value":"","href":"/pages/article.html?article=archive-npc-item-5486-roxxy","html":""},{"value":"","href":"/pages/article.html?article=archive-npc-item-5486-roxxy","html":""}],"meta":[]},{"id":"row-3","title":"","href":"/pages/article.html?article=archive-npc-item-5486-roxxy","cells":[{"value":"Уровень","href":"/pages/article.html?article=archive-npc-item-5486-roxxy","html":""},{"value":"70","href":"/pages/article.html?article=archive-npc-item-5486-roxxy","html":""},{"value":"","href":"/pages/article.html?article=archive-npc-item-5486-roxxy","html":""}],"meta":[]},{"id":"row-4","title":"","href":"/pages/article.html?article=archive-npc-item-5486-roxxy","cells":[{"value":"Раса","href":"/pages/article.html?article=archive-npc-item-5486-roxxy","html":""},{"value":"Humans","href":"/pages/article.html?article=archive-npc-item-5486-roxxy","html":""},{"value":"","href":"/pages/article.html?article=archive-npc-item-5486-roxxy","html":""}],"meta":[]},{"id":"row-5","title":"","href":"/pages/article.html?article=archive-npc-item-5486-roxxy","cells":[{"value":"Агрессивный","href":"/pages/article.html?article=archive-npc-item-5486-roxxy","html":""},{"value":"Нет","href":"/pages/article.html?article=archive-npc-item-5486-roxxy","html":""},{"value":"","href":"/pages/article.html?article=archive-npc-item-5486-roxxy","html":""}],"meta":[]},{"id":"row-6","title":"","href":"/pages/article.html?article=archive-npc-item-5486-roxxy","cells":[{"value":"Количество HP","href":"/pages/article.html?article=archive-npc-item-5486-roxxy","html":""},{"value":"3862","href":"/pages/article.html?article=archive-npc-item-5486-roxxy","html":""},{"value":"","href":"/pages/article.html?article=archive-npc-item-5486-roxxy","html":""}],"meta":[]},{"id":"row-7","title":"","href":"/pages/article.html?article=archive-npc-item-5486-roxxy","cells":[{"value":"Количество MP","href":"/pages/article.html?article=archive-npc-item-5486-roxxy","html":""},{"value":"1493","href":"/pages/article.html?article=archive-npc-item-5486-roxxy","html":""},{"value":"","href":"/pages/article.html?article=archive-npc-item-5486-roxxy","html":""}],"meta":[]},{"id":"row-8","title":"","href":"/pages/article.html?article=archive-npc-item-5486-roxxy","cells":[{"value":"Количество EXP","href":"/pages/article.html?article=archive-npc-item-5486-roxxy","html":""},{"value":"-","href":"/pages/article.html?article=archive-npc-item-5486-roxxy","html":""},{"value":"","href":"/pages/article.html?article=archive-npc-item-5486-roxxy","html":""}],"meta":[]},{"id":"row-9","title":"","href":"/pages/article.html?article=archive-npc-item-5486-roxxy","cells":[{"value":"Количество SP","href":"/pages/article.html?article=archive-npc-item-5486-roxxy","html":""},{"value":"-","href":"/pages/article.html?article=archive-npc-item-5486-roxxy","html":""},{"value":"","href":"/pages/article.html?article=archive-npc-item-5486-roxxy","html":""}],"meta":[]}],"compact":true},{"id":"npc-item-5486-roxxy-block-3","type":"list","title":"","style":"unordered","items":["Квесты","Местонахождение"]},{"id":"npc-item-5486-roxxy-block-4","type":"prose","title":"Квесты","paragraphs":["Можно взять квест:"]},{"id":"npc-item-5486-roxxy-block-5","type":"table","title":"","columns":[{"key":"column-1","label":"Название","align":"","width":""},{"key":"column-2","label":"Уров.","align":"","width":""},{"key":"column-3","label":"Тип","align":"","width":""},{"key":"column-4","label":"Требования","align":"","width":""},{"key":"column-5","label":"Старт. NPC","align":"","width":""},{"key":"column-6","label":"Старт. локация","align":"","width":""},{"key":"column-7","label":"Награда","align":"","width":""}],"rows":[{"id":"row-1","title":"","href":"/pages/article.html?article=archive-npc-item-5486-roxxy","cells":[{"value":"Step into the Future / (Шаг в будущее)","href":"/pages/article.html?article=archive-quests-item-2865-step-into-the-future","html":""},{"value":"3 - 10","href":"/pages/article.html?article=archive-npc-item-5486-roxxy","html":""},{"value":"Одноразовый квест Выполняется в одного","href":"/pages/article.html?article=archive-npc-item-5486-roxxy","html":""},{"value":"Человек","href":"/pages/article.html?article=archive-npc-item-5486-roxxy","html":""},{"value":"Gatekeeper Roxxy / (Хранитель Портала Рокси)","href":"/pages/article.html?article=archive-npc-item-5486-roxxy","html":""},{"value":"Gludio Territory / (Земли Глудио)","href":"/pages/article.html?article=archive-npc-item-5486-roxxy","html":""},{"value":"Scroll of Escape: Town of Giran (Свиток Телепорта: Гиран) - 1 шт. / Mark of Traveler (Знак Путешественника)","href":"/pages/article.html?article=archive-npc-item-5486-roxxy","html":""}],"meta":[]}],"compact":true},{"id":"npc-item-5486-roxxy-block-6","type":"prose","title":"","paragraphs":["Участвует в квестах:"]},{"id":"npc-item-5486-roxxy-block-7","type":"table","title":"","columns":[{"key":"column-1","label":"Название","align":"","width":""},{"key":"column-2","label":"Уров.","align":"","width":""},{"key":"column-3","label":"Тип","align":"","width":""},{"key":"column-4","label":"Требования","align":"","width":""},{"key":"column-5","label":"Старт. NPC","align":"","width":""},{"key":"column-6","label":"Старт. локация","align":"","width":""},{"key":"column-7","label":"Награда","align":"","width":""}],"rows":[{"id":"row-1","title":"","href":"/pages/article.html?article=archive-npc-item-5486-roxxy","cells":[{"value":"Letters of Love / (Любовное послание)","href":"/pages/article.html?article=archive-quests-item-2858-letters-of-love","html":""},{"value":"2-5","href":"/pages/article.html?article=archive-npc-item-5486-roxxy","html":""},{"value":"Одноразовый квест Выполняется в одного","href":"/pages/article.html?article=archive-npc-item-5486-roxxy","html":""},{"value":"Нет требований","href":"/pages/article.html?article=archive-npc-item-5486-roxxy","html":""},{"value":"Darin / (Дарин)","href":"/pages/article.html?article=archive-npc-item-5486-roxxy","html":""},{"value":"Gludio Territory / (Земли Глудио)","href":"/pages/article.html?article=archive-npc-item-5486-roxxy","html":""},{"value":"Necklace of Knowledge (Ожерелье Знаний) - 1 шт.","href":"/pages/section.html?section=items","html":""}],"meta":[]}],"compact":true}]}