{"id":"archive-monster-item-5202-paliote","section":"monsters","group":"m-r","title":"Paliote (Палиот)","summary":"Paliote (Палиот) - спойл, дроп, характеристики, местонахождение","eyebrow":"Монстры","meta":[],"intro":[],"checklist":[],"steps":[],"rewards":[],"tips":[],"related":[],"order":75,"layout":"detail","sidebarFacts":[],"source":{"url":"https://web.archive.org/web/20191023202012/http://l2int.ru:80/monster/item/5202-paliote","archivedAt":"20191023202012","path":"monster/item/5202-paliote","snapshot":"data/raw/archive/monster-item-5202-paliote--20191023202012.html","sourceType":"local-archive"},"aliases":["paliote (палиот)","paliote","палиот"],"heroImage":"/assets/img/archive/quest-potion-gold-e610cde97b36.jpg","blocks":[{"id":"monster-item-5202-paliote-block-1","type":"list","title":"","style":"unordered","items":["Interlude"]},{"id":"monster-item-5202-paliote-block-2","type":"table","title":"Interlude","columns":[{"key":"column-1","label":"Колонка 1","align":"","width":""},{"key":"column-2","label":"Колонка 2","align":"","width":""},{"key":"column-3","label":"Колонка 3","align":"","width":""}],"rows":[{"id":"row-1","title":"","href":"/pages/article.html?article=archive-monster-item-5202-paliote","cells":[{"value":"Уровень / 57 / Раса / Magic Creatures / Агрессивный / Нет / Количество HP / 2806 / Количество MP / 1052 / Количество EXP / 4094 / Количество SP / 340","href":"/pages/article.html?article=archive-monster-item-5202-paliote","html":""},{"value":"P.Atk (Физ. Атака) / 817 / P.Def (Физ. Защита) / 309 / M.Atk (Маг. Атака) / 405 / M.Def (Маг. Защита) / 276 / Пассивные навыки / / Активные навыки / Slightly Weak P. Def. Slightly Strong P. Atk. Slightly Strong M. Atk. HP Increase (2x) Decrease Speed","href":"/pages/article.html?article=archive-monster-item-5202-paliote","html":""},{"value":"Скриншот не загружен","href":"/pages/article.html?article=archive-monster-item-5202-paliote","html":""}],"meta":[]},{"id":"row-2","title":"","href":"/pages/article.html?article=archive-monster-item-5202-paliote","cells":[{"value":"Уровень","href":"/pages/article.html?article=archive-monster-item-5202-paliote","html":""},{"value":"57","href":"/pages/article.html?article=archive-monster-item-5202-paliote","html":""},{"value":"","href":"/pages/article.html?article=archive-monster-item-5202-paliote","html":""}],"meta":[]},{"id":"row-3","title":"","href":"/pages/article.html?article=archive-monster-item-5202-paliote","cells":[{"value":"Раса","href":"/pages/article.html?article=archive-monster-item-5202-paliote","html":""},{"value":"Magic Creatures","href":"/pages/article.html?article=archive-monster-item-5202-paliote","html":""},{"value":"","href":"/pages/article.html?article=archive-monster-item-5202-paliote","html":""}],"meta":[]},{"id":"row-4","title":"","href":"/pages/article.html?article=archive-monster-item-5202-paliote","cells":[{"value":"Агрессивный","href":"/pages/article.html?article=archive-monster-item-5202-paliote","html":""},{"value":"Нет","href":"/pages/article.html?article=archive-monster-item-5202-paliote","html":""},{"value":"","href":"/pages/article.html?article=archive-monster-item-5202-paliote","html":""}],"meta":[]},{"id":"row-5","title":"","href":"/pages/article.html?article=archive-monster-item-5202-paliote","cells":[{"value":"Количество HP","href":"/pages/article.html?article=archive-monster-item-5202-paliote","html":""},{"value":"2806","href":"/pages/article.html?article=archive-monster-item-5202-paliote","html":""},{"value":"","href":"/pages/article.html?article=archive-monster-item-5202-paliote","html":""}],"meta":[]},{"id":"row-6","title":"","href":"/pages/article.html?article=archive-monster-item-5202-paliote","cells":[{"value":"Количество MP","href":"/pages/article.html?article=archive-monster-item-5202-paliote","html":""},{"value":"1052","href":"/pages/article.html?article=archive-monster-item-5202-paliote","html":""},{"value":"","href":"/pages/article.html?article=archive-monster-item-5202-paliote","html":""}],"meta":[]},{"id":"row-7","title":"","href":"/pages/article.html?article=archive-monster-item-5202-paliote","cells":[{"value":"Количество EXP","href":"/pages/article.html?article=archive-monster-item-5202-paliote","html":""},{"value":"4094","href":"/pages/article.html?article=archive-monster-item-5202-paliote","html":""},{"value":"","href":"/pages/article.html?article=archive-monster-item-5202-paliote","html":""}],"meta":[]},{"id":"row-8","title":"","href":"/pages/article.html?article=archive-monster-item-5202-paliote","cells":[{"value":"Количество SP","href":"/pages/article.html?article=archive-monster-item-5202-paliote","html":""},{"value":"340","href":"/pages/article.html?article=archive-monster-item-5202-paliote","html":""},{"value":"","href":"/pages/article.html?article=archive-monster-item-5202-paliote","html":""}],"meta":[]},{"id":"row-9","title":"","href":"/pages/article.html?article=archive-monster-item-5202-paliote","cells":[{"value":"P.Atk (Физ. Атака)","href":"/pages/article.html?article=archive-monster-item-5202-paliote","html":""},{"value":"817","href":"/pages/article.html?article=archive-monster-item-5202-paliote","html":""},{"value":"","href":"/pages/article.html?article=archive-monster-item-5202-paliote","html":""}],"meta":[]},{"id":"row-10","title":"","href":"/pages/article.html?article=archive-monster-item-5202-paliote","cells":[{"value":"P.Def (Физ. Защита)","href":"/pages/article.html?article=archive-monster-item-5202-paliote","html":""},{"value":"309","href":"/pages/article.html?article=archive-monster-item-5202-paliote","html":""},{"value":"","href":"/pages/article.html?article=archive-monster-item-5202-paliote","html":""}],"meta":[]},{"id":"row-11","title":"","href":"/pages/article.html?article=archive-monster-item-5202-paliote","cells":[{"value":"M.Atk (Маг. Атака)","href":"/pages/article.html?article=archive-monster-item-5202-paliote","html":""},{"value":"405","href":"/pages/article.html?article=archive-monster-item-5202-paliote","html":""},{"value":"","href":"/pages/article.html?article=archive-monster-item-5202-paliote","html":""}],"meta":[]},{"id":"row-12","title":"","href":"/pages/article.html?article=archive-monster-item-5202-paliote","cells":[{"value":"M.Def (Маг. Защита)","href":"/pages/article.html?article=archive-monster-item-5202-paliote","html":""},{"value":"276","href":"/pages/article.html?article=archive-monster-item-5202-paliote","html":""},{"value":"","href":"/pages/article.html?article=archive-monster-item-5202-paliote","html":""}],"meta":[]},{"id":"row-13","title":"","href":"/pages/article.html?article=archive-monster-item-5202-paliote","cells":[{"value":"Пассивные навыки","href":"/pages/article.html?article=archive-monster-item-5202-paliote","html":""},{"value":"","href":"/pages/article.html?article=archive-monster-item-5202-paliote","html":""},{"value":"","href":"/pages/article.html?article=archive-monster-item-5202-paliote","html":""}],"meta":[]},{"id":"row-14","title":"","href":"/pages/article.html?article=archive-monster-item-5202-paliote","cells":[{"value":"Slightly Weak P. Def. Slightly Strong P. Atk. Slightly Strong M. Atk. HP Increase (2x)","href":"/pages/article.html?article=archive-monster-item-5202-paliote","html":""},{"value":"","href":"/pages/article.html?article=archive-monster-item-5202-paliote","html":""},{"value":"","href":"/pages/article.html?article=archive-monster-item-5202-paliote","html":""}],"meta":[]},{"id":"row-15","title":"","href":"/pages/article.html?article=archive-monster-item-5202-paliote","cells":[{"value":"Активные навыки","href":"/pages/article.html?article=archive-monster-item-5202-paliote","html":""},{"value":"","href":"/pages/article.html?article=archive-monster-item-5202-paliote","html":""},{"value":"","href":"/pages/article.html?article=archive-monster-item-5202-paliote","html":""}],"meta":[]},{"id":"row-16","title":"","href":"/pages/article.html?article=archive-monster-item-5202-paliote","cells":[{"value":"Decrease Speed","href":"/pages/article.html?article=archive-monster-item-5202-paliote","html":""},{"value":"","href":"/pages/article.html?article=archive-monster-item-5202-paliote","html":""},{"value":"","href":"/pages/article.html?article=archive-monster-item-5202-paliote","html":""}],"meta":[]}],"compact":true},{"id":"monster-item-5202-paliote-block-3","type":"list","title":"","style":"unordered","items":["Дроп","Спойл","Квесты","Местонахождение"]},{"id":"monster-item-5202-paliote-block-4","type":"table","title":"Дроп","columns":[{"key":"column-1","label":"Колонка 1","align":"","width":""},{"key":"column-2","label":"Название предмета","align":"","width":""},{"key":"column-3","label":"Кол-во","align":"","width":""},{"key":"column-4","label":"Шанс","align":"","width":""}],"rows":[{"id":"row-1","title":"","href":"/pages/article.html?article=archive-monster-item-5202-paliote","cells":[{"value":"","href":"/pages/article.html?article=archive-monster-item-5202-paliote","html":""},{"value":"Adena","href":"/pages/article.html?article=archive-monster-item-5202-paliote","html":""},{"value":"1033 - 2109","href":"/pages/article.html?article=archive-monster-item-5202-paliote","html":""},{"value":"70.0000%","href":"/pages/article.html?article=archive-monster-item-5202-paliote","html":""}],"meta":[]},{"id":"row-2","title":"","href":"/pages/article.html?article=archive-monster-item-5202-paliote","cells":[{"value":"","href":"/pages/article.html?article=archive-monster-item-5202-paliote","html":""},{"value":"Thread","href":"/pages/section.html?section=items","html":""},{"value":"1 - 1","href":"/pages/article.html?article=archive-monster-item-5202-paliote","html":""},{"value":"18.9555%","href":"/pages/article.html?article=archive-monster-item-5202-paliote","html":""}],"meta":[]},{"id":"row-3","title":"","href":"/pages/article.html?article=archive-monster-item-5202-paliote","cells":[{"value":"","href":"/pages/article.html?article=archive-monster-item-5202-paliote","html":""},{"value":"Silver Nugget","href":"/pages/section.html?section=items","html":""},{"value":"1 - 1","href":"/pages/article.html?article=archive-monster-item-5202-paliote","html":""},{"value":"3.7911%","href":"/pages/article.html?article=archive-monster-item-5202-paliote","html":""}],"meta":[]},{"id":"row-4","title":"","href":"/pages/article.html?article=archive-monster-item-5202-paliote","cells":[{"value":"","href":"/pages/article.html?article=archive-monster-item-5202-paliote","html":""},{"value":"Metallic Fiber","href":"/pages/section.html?section=items","html":""},{"value":"1 - 1","href":"/pages/article.html?article=archive-monster-item-5202-paliote","html":""},{"value":"2.7080%","href":"/pages/article.html?article=archive-monster-item-5202-paliote","html":""}],"meta":[]},{"id":"row-5","title":"","href":"/pages/article.html?article=archive-monster-item-5202-paliote","cells":[{"value":"","href":"/pages/article.html?article=archive-monster-item-5202-paliote","html":""},{"value":"Deluxe Chest Key - Grade 5","href":"/pages/article.html?article=archive-monster-item-5202-paliote","html":""},{"value":"1 - 1","href":"/pages/article.html?article=archive-monster-item-5202-paliote","html":""},{"value":"2.2042%","href":"/pages/article.html?article=archive-monster-item-5202-paliote","html":""}],"meta":[]},{"id":"row-6","title":"","href":"/pages/article.html?article=archive-monster-item-5202-paliote","cells":[{"value":"","href":"/pages/article.html?article=archive-monster-item-5202-paliote","html":""},{"value":"Mithril Ore","href":"/pages/section.html?section=items","html":""},{"value":"1 - 1","href":"/pages/article.html?article=archive-monster-item-5202-paliote","html":""},{"value":"1.8956%","href":"/pages/article.html?article=archive-monster-item-5202-paliote","html":""}],"meta":[]},{"id":"row-7","title":"","href":"/pages/article.html?article=archive-monster-item-5202-paliote","cells":[{"value":"","href":"/pages/article.html?article=archive-monster-item-5202-paliote","html":""},{"value":"Avadon Boots Design","href":"/pages/section.html?section=items","html":""},{"value":"1 - 1","href":"/pages/article.html?article=archive-monster-item-5202-paliote","html":""},{"value":"0.4932%","href":"/pages/article.html?article=archive-monster-item-5202-paliote","html":""}],"meta":[]},{"id":"row-8","title":"","href":"/pages/article.html?article=archive-monster-item-5202-paliote","cells":[{"value":"","href":"/pages/article.html?article=archive-monster-item-5202-paliote","html":""},{"value":"Zubei's Gauntlets Part","href":"/pages/section.html?section=items","html":""},{"value":"1 - 1","href":"/pages/article.html?article=archive-monster-item-5202-paliote","html":""},{"value":"0.4932%","href":"/pages/article.html?article=archive-monster-item-5202-paliote","html":""}],"meta":[]},{"id":"row-9","title":"","href":"/pages/article.html?article=archive-monster-item-5202-paliote","cells":[{"value":"","href":"/pages/article.html?article=archive-monster-item-5202-paliote","html":""},{"value":"Avadon Gloves Part","href":"/pages/section.html?section=items","html":""},{"value":"1 - 1","href":"/pages/article.html?article=archive-monster-item-5202-paliote","html":""},{"value":"0.4932%","href":"/pages/article.html?article=archive-monster-item-5202-paliote","html":""}],"meta":[]},{"id":"row-10","title":"","href":"/pages/article.html?article=archive-monster-item-5202-paliote","cells":[{"value":"","href":"/pages/article.html?article=archive-monster-item-5202-paliote","html":""},{"value":"Zubei's Boots Design","href":"/pages/section.html?section=items","html":""},{"value":"1 - 1","href":"/pages/article.html?article=archive-monster-item-5202-paliote","html":""},{"value":"0.4932%","href":"/pages/article.html?article=archive-monster-item-5202-paliote","html":""}],"meta":[]},{"id":"row-11","title":"","href":"/pages/article.html?article=archive-monster-item-5202-paliote","cells":[{"value":"","href":"/pages/article.html?article=archive-monster-item-5202-paliote","html":""},{"value":"Recipe: Zubei's Shield (60%)","href":"/pages/section.html?section=items","html":""},{"value":"1 - 1","href":"/pages/article.html?article=archive-monster-item-5202-paliote","html":""},{"value":"0.1740%","href":"/pages/article.html?article=archive-monster-item-5202-paliote","html":""}],"meta":[]},{"id":"row-12","title":"","href":"/pages/article.html?article=archive-monster-item-5202-paliote","cells":[{"value":"","href":"/pages/article.html?article=archive-monster-item-5202-paliote","html":""},{"value":"Enria","href":"/pages/section.html?section=items","html":""},{"value":"1 - 1","href":"/pages/article.html?article=archive-monster-item-5202-paliote","html":""},{"value":"0.1580%","href":"/pages/article.html?article=archive-monster-item-5202-paliote","html":""}],"meta":[]},{"id":"row-13","title":"","href":"/pages/article.html?article=archive-monster-item-5202-paliote","cells":[{"value":"","href":"/pages/article.html?article=archive-monster-item-5202-paliote","html":""},{"value":"Recipe: Doom Boots (60%)","href":"/pages/section.html?section=items","html":""},{"value":"1 - 1","href":"/pages/article.html?article=archive-monster-item-5202-paliote","html":""},{"value":"0.1179%","href":"/pages/article.html?article=archive-monster-item-5202-paliote","html":""}],"meta":[]},{"id":"row-14","title":"","href":"/pages/article.html?article=archive-monster-item-5202-paliote","cells":[{"value":"","href":"/pages/article.html?article=archive-monster-item-5202-paliote","html":""},{"value":"Avadon Boots","href":"/pages/section.html?section=items","html":""},{"value":"1 - 1","href":"/pages/article.html?article=archive-monster-item-5202-paliote","html":""},{"value":"0.0037%","href":"/pages/article.html?article=archive-monster-item-5202-paliote","html":""}],"meta":[]},{"id":"row-15","title":"","href":"/pages/article.html?article=archive-monster-item-5202-paliote","cells":[{"value":"","href":"/pages/article.html?article=archive-monster-item-5202-paliote","html":""},{"value":"Avadon Gloves","href":"/pages/section.html?section=items","html":""},{"value":"1 - 1","href":"/pages/article.html?article=archive-monster-item-5202-paliote","html":""},{"value":"0.0037%","href":"/pages/article.html?article=archive-monster-item-5202-paliote","html":""}],"meta":[]},{"id":"row-16","title":"","href":"/pages/article.html?article=archive-monster-item-5202-paliote","cells":[{"value":"","href":"/pages/article.html?article=archive-monster-item-5202-paliote","html":""},{"value":"Zubei's Boots","href":"/pages/section.html?section=items","html":""},{"value":"1 - 1","href":"/pages/article.html?article=archive-monster-item-5202-paliote","html":""},{"value":"0.0037%","href":"/pages/article.html?article=archive-monster-item-5202-paliote","html":""}],"meta":[]},{"id":"row-17","title":"","href":"/pages/article.html?article=archive-monster-item-5202-paliote","cells":[{"value":"","href":"/pages/article.html?article=archive-monster-item-5202-paliote","html":""},{"value":"Zubei's Gauntlets","href":"/pages/section.html?section=items","html":""},{"value":"1 - 1","href":"/pages/article.html?article=archive-monster-item-5202-paliote","html":""},{"value":"0.0037%","href":"/pages/article.html?article=archive-monster-item-5202-paliote","html":""}],"meta":[]}],"compact":true},{"id":"monster-item-5202-paliote-block-5","type":"table","title":"Спойл","columns":[{"key":"column-1","label":"Колонка 1","align":"","width":""},{"key":"column-2","label":"Название предмета","align":"","width":""},{"key":"column-3","label":"Кол-во","align":"","width":""},{"key":"column-4","label":"Шанс","align":"","width":""}],"rows":[{"id":"row-1","title":"","href":"/pages/article.html?article=archive-monster-item-5202-paliote","cells":[{"value":"","href":"/pages/article.html?article=archive-monster-item-5202-paliote","html":""},{"value":"Thread","href":"/pages/section.html?section=items","html":""},{"value":"1 - 11","href":"/pages/article.html?article=archive-monster-item-5202-paliote","html":""},{"value":"85.5624%","href":"/pages/article.html?article=archive-monster-item-5202-paliote","html":""}],"meta":[]},{"id":"row-2","title":"","href":"/pages/article.html?article=archive-monster-item-5202-paliote","cells":[{"value":"","href":"/pages/article.html?article=archive-monster-item-5202-paliote","html":""},{"value":"Full Plate Gauntlets Part","href":"/pages/section.html?section=items","html":""},{"value":"1 - 1","href":"/pages/article.html?article=archive-monster-item-5202-paliote","html":""},{"value":"13.9770%","href":"/pages/article.html?article=archive-monster-item-5202-paliote","html":""}],"meta":[]},{"id":"row-3","title":"","href":"/pages/article.html?article=archive-monster-item-5202-paliote","cells":[{"value":"","href":"/pages/article.html?article=archive-monster-item-5202-paliote","html":""},{"value":"Recipe: Great Axe (100%)","href":"/pages/section.html?section=items","html":""},{"value":"1 - 1","href":"/pages/article.html?article=archive-monster-item-5202-paliote","html":""},{"value":"0.2957%","href":"/pages/article.html?article=archive-monster-item-5202-paliote","html":""}],"meta":[]}],"compact":true},{"id":"monster-item-5202-paliote-block-6","type":"table","title":"Квесты","columns":[{"key":"column-1","label":"Название","align":"","width":""},{"key":"column-2","label":"Уров.","align":"","width":""},{"key":"column-3","label":"Тип","align":"","width":""},{"key":"column-4","label":"Требования","align":"","width":""},{"key":"column-5","label":"Старт. NPC","align":"","width":""},{"key":"column-6","label":"Старт. локация","align":"","width":""},{"key":"column-7","label":"Награда","align":"","width":""}],"rows":[{"id":"row-1","title":"","href":"/pages/article.html?article=archive-monster-item-5202-paliote","cells":[{"value":"Quest for Fishing Shot / (Поплавки для рыбалки)","href":"/pages/article.html?article=archive-quests-item-2836-quest-for-fishing-shot","html":""},{"value":"1 - 80","href":"/pages/article.html?article=archive-monster-item-5202-paliote","html":""},{"value":"Повторяемый квест Можно выполнять в группе","href":"/pages/article.html?article=archive-monster-item-5202-paliote","html":""},{"value":"Нет требований","href":"/pages/article.html?article=archive-monster-item-5202-paliote","html":""},{"value":"Fishing Guild Member","href":"/pages/article.html?article=archive-monster-item-5202-paliote","html":""},{"value":"-","href":"/pages/article.html?article=archive-monster-item-5202-paliote","html":""},{"value":"Fishing Shot (No-grade) (Поплавок: Без Ранга) / Fishing Shot (D-grade) (Поплавок: Ранг D) / Fishing Shot (C-grade) (Поплавок: Ранг C) / Fishing Shot (B-grade) (Поплавок: Ранг B) / Fishing Shot (A-grade) (Поплавок: Ранг A) / Fishing Shot (S-grade) (Поплавок: Ранг S)","href":"/pages/article.html?article=archive-monster-item-5202-paliote","html":""}],"meta":[]},{"id":"row-2","title":"","href":"/pages/article.html?article=archive-monster-item-5202-paliote","cells":[{"value":"Enhance Your Weapon / (Усиление оружия)","href":"/pages/article.html?article=soul-crystal","html":""},{"value":"40+","href":"/pages/article.html?article=archive-monster-item-5202-paliote","html":""},{"value":"Повторяемый квест Выполняется в одного","href":"/pages/article.html?article=archive-monster-item-5202-paliote","html":""},{"value":"Нет требований","href":"/pages/article.html?article=archive-monster-item-5202-paliote","html":""},{"value":"-","href":"/pages/article.html?article=archive-monster-item-5202-paliote","html":""},{"value":"-","href":"/pages/article.html?article=archive-monster-item-5202-paliote","html":""},{"value":"Red Soul Crystal / Blue Soul Crystal / Green Soul Crystal","href":"/pages/article.html?article=archive-monster-item-5202-paliote","html":""}],"meta":[]},{"id":"row-3","title":"","href":"/pages/article.html?article=archive-monster-item-5202-paliote","cells":[{"value":"An Arrogant Search / (Самонадеянный поиск)","href":"/pages/article.html?article=archive-monster-item-5202-paliote","html":""},{"value":"60 - 75","href":"/pages/article.html?article=archive-monster-item-5202-paliote","html":""},{"value":"Повторяемый квест Можно выполнить в группе","href":"/pages/article.html?article=archive-monster-item-5202-paliote","html":""},{"value":"Нет требований","href":"/pages/article.html?article=archive-monster-item-5202-paliote","html":""},{"value":"Magister Hanellin / (Магистр Ханелин)","href":"/pages/article.html?article=archive-monster-item-5202-paliote","html":""},{"value":"Aden Territory / (Земли Адена)","href":"/pages/article.html?article=archive-monster-item-5202-paliote","html":""},{"value":"Blooded Fabric (Окровавленная Ткань)","href":"/pages/article.html?article=archive-monster-item-5202-paliote","html":""}],"meta":[]},{"id":"row-4","title":"","href":"/pages/article.html?article=archive-monster-item-5202-paliote","cells":[{"value":"The Oppressor and The Oppressed / (Ведущий и ведомый)","href":"/pages/section.html?section=quests","html":""},{"value":"61 - 64","href":"/pages/article.html?article=archive-monster-item-5202-paliote","html":""},{"value":"Ежедневный квест Выполняется в одного","href":"/pages/article.html?article=archive-monster-item-5202-paliote","html":""},{"value":"Нет требований","href":"/pages/article.html?article=archive-monster-item-5202-paliote","html":""},{"value":"Adventurer Helper / (Гид Путешественников)","href":"/pages/article.html?article=archive-monster-item-5202-paliote","html":""},{"value":"-","href":"/pages/article.html?article=archive-monster-item-5202-paliote","html":""},{"value":"194,000 Adena / 1,879,400 EXP / 1,782,000 SP","href":"/pages/article.html?article=archive-monster-item-5202-paliote","html":""}],"meta":[]}],"compact":true}]}