{"id":"armor-item-399-hoplon","section":"items","group":"armor","title":"Hoplon (Хоплон)","summary":"Физ. Защ. \\ P. Def: 128 • Вес \\ Weight: 1340 • Цена \\ Price: 41,000 Adena","eyebrow":"Предметы | Щиты","meta":[{"label":"Физ. Защ. \\ P. Def","value":"128"},{"label":"Шанс Блока \\ Def. Rate","value":"20"},{"label":"Уворот","value":"-8"},{"label":"Вес \\ Weight","value":"1340"}],"intro":["Hoplon (Хоплон) — локальная копия предмета с данными и таблицами, собранными по структуре l2int.ru."],"checklist":[],"steps":[],"rewards":[],"tips":[],"related":["items-armor-shields","items-armor"],"order":0,"layout":"detail","sidebarFacts":[{"label":"Физ. Защ. \\ P. Def","value":"128"},{"label":"Шанс Блока \\ Def. Rate","value":"20"},{"label":"Уворот","value":"-8"},{"label":"Вес \\ Weight","value":"1340"}],"source":{"url":"https://l2int.ru/predmety/bronya/shields/d/item/399-hoplon","path":"predmety/bronya/shields/d/item/399-hoplon","snapshot":"live-import-2026-04-12","sourceType":"reference"},"aliases":["hoplon","хоплон"],"heroImage":"https://l2int.ru/images/armor_weapon/armor/D/Hoplon.jpg","blocks":[{"id":"armor-item-399-hoplon-hero","type":"media","title":"","items":[{"src":"https://l2int.ru/images/armor_weapon/armor/D/Hoplon.jpg","alt":"Hoplon (Хоплон)","caption":"Hoplon (Хоплон)"}]},{"id":"armor-item-399-hoplon-stats","type":"table","title":"Основные параметры","columns":[{"key":"fact","label":"Параметр","align":"","width":""},{"key":"value","label":"Значение","align":"","width":""}],"rows":[{"id":"row-1","title":"","href":"","cells":[{"value":"Физ. Защ. \\ P. Def","href":"","html":""},{"value":"128","href":"","html":""}],"meta":[]},{"id":"row-2","title":"","href":"","cells":[{"value":"Шанс Блока \\ Def. Rate","href":"","html":""},{"value":"20","href":"","html":""}],"meta":[]},{"id":"row-3","title":"","href":"","cells":[{"value":"Уворот","href":"","html":""},{"value":"-8","href":"","html":""}],"meta":[]},{"id":"row-4","title":"","href":"","cells":[{"value":"Вес \\ Weight","href":"","html":""},{"value":"1340","href":"","html":""}],"meta":[]},{"id":"row-5","title":"","href":"","cells":[{"value":"Цена \\ Price","href":"","html":""},{"value":"41,000 Adena","href":"","html":""}],"meta":[]},{"id":"row-6","title":"","href":"","cells":[{"value":"Ранг \\ Grade","href":"","html":""},{"value":"D Grade","href":"","html":""}],"meta":[]},{"id":"row-7","title":"","href":"","cells":[{"value":"Количество кристаллов при разбитии","href":"","html":""},{"value":"76","href":"","html":""}],"meta":[]},{"id":"row-8","title":"","href":"","cells":[{"value":"Уровень Крафта \\Create Item","href":"","html":""},{"value":"-","href":"","html":""}],"meta":[]}],"compact":true},{"id":"armor-item-399-hoplon-table-1","type":"table","title":"Дроп","columns":[{"key":"column-1","label":"Имя Монстра","align":"","width":""},{"key":"column-2","label":"Ур.","align":"","width":""},{"key":"column-3","label":"Кол-во","align":"","width":""},{"key":"column-4","label":"Шанс","align":"","width":""}],"rows":[{"id":"row-1","title":"","href":"","cells":[{"value":"Betrayer of Urutu Freki","href":"/pages/article.html?article=archive-monster-item-4193-betrayer-of-urutu-freki","html":""},{"value":"25","href":"","html":""},{"value":"1 — 3","href":"","html":""},{"value":"32.1734%","href":"","html":""}],"meta":[]},{"id":"row-2","title":"","href":"","cells":[{"value":"Anakazel","href":"/pages/article.html?article=archive-monster-item-4265-anakazel","html":""},{"value":"28","href":"","html":""},{"value":"1 — 3","href":"","html":""},{"value":"32.0820%","href":"","html":""}],"meta":[]},{"id":"row-3","title":"","href":"","cells":[{"value":"Otherworldly Invader Magus","href":"/pages/article.html?article=archive-monster-item-4403-otherworldly-invader-magus","html":""},{"value":"33","href":"","html":""},{"value":"1 — 1","href":"","html":""},{"value":"0.2681%","href":"","html":""}],"meta":[]},{"id":"row-4","title":"","href":"","cells":[{"value":"Gigant Cleric","href":"/pages/article.html?article=archive-monster-item-4389-gigant-cleric","html":""},{"value":"33","href":"","html":""},{"value":"1 — 1","href":"","html":""},{"value":"0.1611%","href":"","html":""}],"meta":[]},{"id":"row-5","title":"","href":"","cells":[{"value":"Lith Medium","href":"/pages/article.html?article=archive-monster-item-4390-lith-medium","html":""},{"value":"33","href":"","html":""},{"value":"1 — 1","href":"","html":""},{"value":"0.1611%","href":"","html":""}],"meta":[]},{"id":"row-6","title":"","href":"","cells":[{"value":"Otherworldly Invader Warrior","href":"/pages/article.html?article=archive-monster-item-4418-otherworldly-invader-warrior","html":""},{"value":"33","href":"","html":""},{"value":"1 — 1","href":"","html":""},{"value":"0.1209%","href":"","html":""}],"meta":[]},{"id":"row-7","title":"","href":"","cells":[{"value":"Marsh Stakato Soldier","href":"/pages/article.html?article=archive-monster-item-4406-marsh-stakato-soldier","html":""},{"value":"33","href":"","html":""},{"value":"1 — 1","href":"","html":""},{"value":"0.0527%","href":"","html":""}],"meta":[]},{"id":"row-8","title":"","href":"","cells":[{"value":"Catacomb Shadow","href":"/pages/article.html?article=archive-monster-item-4435-catacomb-shadow","html":""},{"value":"34","href":"","html":""},{"value":"1 — 1","href":"","html":""},{"value":"0.1657%","href":"","html":""}],"meta":[]},{"id":"row-9","title":"","href":"","cells":[{"value":"Cursed Seer","href":"/pages/article.html?article=archive-monster-item-4436-cursed-seer","html":""},{"value":"34","href":"","html":""},{"value":"1 — 1","href":"","html":""},{"value":"0.0567%","href":"","html":""}],"meta":[]},{"id":"row-10","title":"","href":"","cells":[{"value":"Ant Patrol","href":"/pages/article.html?article=archive-monster-item-4443-ant-patrol","html":""},{"value":"34","href":"","html":""},{"value":"1 — 1","href":"","html":""},{"value":"0.0551%","href":"","html":""}],"meta":[]},{"id":"row-11","title":"","href":"","cells":[{"value":"Tyrant Kingpin","href":"/pages/article.html?article=archive-monster-item-4523-tyrant-kingpin","html":""},{"value":"36","href":"","html":""},{"value":"1 — 1","href":"","html":""},{"value":"0.0632%","href":"","html":""}],"meta":[]},{"id":"row-12","title":"","href":"","cells":[{"value":"Treasure Chest","href":"/pages/article.html?article=archive-monster-item-4510-treasure-chest-36","html":""},{"value":"36","href":"","html":""},{"value":"1 — 1","href":"","html":""},{"value":"0.0512%","href":"","html":""}],"meta":[]}],"compact":false},{"id":"armor-item-399-hoplon-table-2","type":"table","title":"Бонусы Набора (Сет)","columns":[{"key":"column-1","label":"Колонка 1","align":"","width":""},{"key":"column-2","label":"Название","align":"","width":""}],"rows":[{"id":"row-1","title":"","href":"","cells":[{"value":"Helmet (Шлем)","href":"/pages/article.html?article=armor-item-920-helmet","html":""}],"meta":[]},{"id":"row-2","title":"","href":"","cells":[{"value":"Mithril Breastplate (Мифриловая Кираса)","href":"/pages/article.html?article=armor-item-1371-mithril-breastplate","html":""}],"meta":[]},{"id":"row-3","title":"","href":"","cells":[{"value":"Mithril Gaiters (Мифриловые Набедренники)","href":"/pages/article.html?article=armor-item-1381-mithril-gaiters","html":""}],"meta":[]},{"id":"row-4","title":"","href":"","cells":[{"value":"Hoplon (Хоплон)","href":"/pages/article.html?article=armor-item-399-hoplon","html":""}],"meta":[]}],"compact":false}]}