{"id":"armor-item-linedia-32565-fantasy-moirai-shoes","section":"items","group":"armor","title":"Fantasy Moirai Shoes (Фантастические Ботинки Дестино)","summary":"Вес: 1070 • S80 Grade","eyebrow":"Предметы | Ботинки","meta":[{"label":"Вес","value":"1070"},{"label":"Ранг","value":"S80 Grade"}],"intro":["Fantasy Moirai Shoes (Фантастические Ботинки Дестино) — локальная карточка предмета, добавленная по данным Linedia для грейда S80 Grade."],"checklist":[],"steps":[],"rewards":[],"tips":[],"related":["items-armor-boots","items-armor"],"order":9999,"layout":"detail","sidebarFacts":[{"label":"Вес","value":"1070"},{"label":"Ранг","value":"S80 Grade"}],"source":{"url":"https://linedia.ru/wiki/Fantasy_Moirai_Shoes_Not_in_Use","path":"wiki/Fantasy_Moirai_Shoes_Not_in_Use","snapshot":"linedia-import-2026-04-25","sourceType":"reference"},"aliases":["fantasy moirai shoes","фантастические ботинки дестино"],"heroImage":"https://linedia.ru/w/images/4/43/Armor_t102_b_i00_0.jpg","blocks":[{"id":"armor-item-linedia-32565-fantasy-moirai-shoes-hero","type":"media","title":"","items":[{"src":"https://linedia.ru/w/images/4/43/Armor_t102_b_i00_0.jpg","alt":"Fantasy Moirai Shoes (Фантастические Ботинки Дестино)","caption":"Fantasy Moirai Shoes (Фантастические Ботинки Дестино)"}]},{"id":"armor-item-linedia-32565-fantasy-moirai-shoes-base-stats","type":"table","title":"Основные параметры","columns":[{"key":"fact","label":"Параметр","align":"","width":""},{"key":"value","label":"Значение","align":"","width":""}],"rows":[{"id":"row-1","title":"","href":"","cells":[{"value":"Тип","href":"","html":""},{"value":"Сапоги (Boots)","href":"","html":""}],"meta":[]},{"id":"row-2","title":"","href":"","cells":[{"value":"P. Def.","href":"","html":""},{"value":"64","href":"","html":""}],"meta":[]},{"id":"row-3","title":"","href":"","cells":[{"value":"Вес","href":"","html":""},{"value":"1070","href":"","html":""}],"meta":[]},{"id":"row-4","title":"","href":"","cells":[{"value":"ID","href":"","html":""},{"value":"32565","href":"","html":""}],"meta":[]},{"id":"row-5","title":"","href":"","cells":[{"value":"Ранг","href":"","html":""},{"value":"S80 Grade","href":"","html":""}],"meta":[]}],"compact":false}]}